cli.py
lexer.py
main.py
parser.py
tree.py
orion_lang-0.2.0.dist-info/licenses/LICENSE
runtime/environment.py
runtime/interpreter.py
runtime/values_.py
runtime/modules/math.py
orion_lang-0.2.0.dist-info/METADATA
orion_lang-0.2.0.dist-info/WHEEL
orion_lang-0.2.0.dist-info/entry_points.txt
orion_lang-0.2.0.dist-info/top_level.txt
orion_lang-0.2.0.dist-info/RECORD
