Metadata-Version: 2.4
Name: orion-lang
Version: 0.2.0
Summary: Orion language interpreter.
Project-URL: Homepage, https://github.com/TheRealArccc/Orion-Language
Project-URL: Repository, https://github.com/TheRealArccc/Orion-Language
Requires-Python: >=3.8
License-File: LICENSE
Dynamic: license-file
